{"stats":{"minecraft:killed":{"smp_mod_v:lushgoblin":5,"smp_mod_v:lushhermitcrab":5,"smp_mod_v:blssomcreature":1},"minecraft:picked_up":{"geckolib3:habitat":1,"geckolib3:fertilizer":1,"smp_mod_v:hermitcrabscut":5},"minecraft:custom":{"minecraft:time_since_rest":35766,"minecraft:crouch_one_cm":3600,"minecraft:sprint_one_cm":14152,"minecraft:play_time":35766,"minecraft:walk_one_cm":124689,"minecraft:sneak_time":1924,"minecraft:interact_with_anvil":9,"minecraft:mob_kills":11,"minecraft:drop":3,"minecraft:jump":89,"minecraft:damage_dealt":1910,"minecraft:leave_game":1,"minecraft:time_since_death":35766,"minecraft:total_world_time":45664,"minecraft:fly_one_cm":6585},"minecraft:used":{"minecraft:farmland":5,"minecraft:oak_log":29,"minecraft:item_frame":5,"minecraft:water_bucket":2,"minecraft:debug_stick":247,"smp_mod_v:alchemytable":5,"smp_mod_v:lushgoblin_spawn_egg":6,"minecraft:anvil":4,"smp_mod_v:emptyjarblock":2,"smp_mod_v:quest_1activator":9,"minecraft:armor_stand":2,"minecraft:grass_block":15,"minecraft:spruce_stairs":1,"smp_mod_v:snaildensign":6,"minecraft:quartz_block":18,"geckolib3:habitat":1,"smp_mod_v:glowberryjar":7,"smp_mod_v:quest_4activator":3,"smp_mod_v:lushhermitcrab_spawn_egg":6,"geckolib3:fertilizer":15,"minecraft:netherite_sword":22,"smp_mod_v:squeezer":4,"smp_mod_v:glowberriejuice":2},"minecraft:dropped":{"geckolib3:fertilizer":1,"geckolib3:habitat":1,"minecraft:grass_block":1}},"DataVersion":3120}